phoenix_parser/__init__.py
phoenix_parser/parser.py
phoenix_parser-0.5.2.dist-info/METADATA
phoenix_parser-0.5.2.dist-info/WHEEL
phoenix_parser-0.5.2.dist-info/licenses/LICENSE
phoenix_parser-0.5.2.dist-info/RECORD
