Metadata-Version: 2.4
Name: phoenix-parser
Version: 0.5.2
Summary: An open, more reliable architecture for parsing LLM output.
Project-URL: Homepage, https://github.com/shalyhinpavel/phoenix
Project-URL: Bug Tracker, https://github.com/shalyhinpavel/phoenix/issues
Author-email: shalyhinpavel <shalyhinpavel@gmail.com>
License:                                  Apache License
License-File: LICENSE
Keywords: ai,json,llm,nlp,parser,pydantic,semantic-parsing
Classifier: Development Status :: 4 - Beta
Classifier: Intended Audience :: Developers
Classifier: License :: OSI Approved :: Apache Software License
Classifier: Operating System :: OS Independent
Classifier: Programming Language :: Python :: 3
Classifier: Topic :: Scientific/Engineering :: Artificial Intelligence
Classifier: Topic :: Software Development :: Libraries :: Python Modules
Classifier: Topic :: Text Processing
Requires-Python: >=3.8
Requires-Dist: pydantic
